WheelDecide
