Metadata-Version: 2.1
Name: WheelDecide
Version: 1.0.1
Summary: This is a package which can make a wheel to decide.
Home-page: https://github.com/Jason4zh/WheelDecide
Author: Jason4zh
Author-email: 13640817984@163.com
Maintainer: Jason4zh
Maintainer-email: 13640817984@163.com
License: BSD License
Platform: all
Classifier: Development Status :: 4 - Beta
Classifier: Operating System :: OS Independent
Classifier: Intended Audience :: Developers
Classifier: License :: OSI Approved :: BSD License
Classifier: Programming Language :: Python
Classifier: Programming Language :: Python :: Implementation
Classifier: Programming Language :: Python :: 2
Classifier: Programming Language :: Python :: 2.7
Classifier: Programming Language :: Python :: 3
Classifier: Programming Language :: Python :: 3.4
Classifier: Programming Language :: Python :: 3.5
Classifier: Programming Language :: Python :: 3.6
Classifier: Topic :: Software Development :: Libraries
License-File: LICENSE
